Metadata-Version: 2.1
Name: odoo14-addon-shopinvader-locomotive-guest-mode
Version: 14.0.1.0.3
Summary: Shopinvader guest mode for locomotive
Home-page: https://github.com/shopinvader/odoo-shopinvader
Author: ACSONE SA/NV,Odoo Community Association (OCA)
Author-email: support@odoo-community.org
License: AGPL-3
Platform: UNKNOWN
Classifier: Programming Language :: Python
Classifier: Framework :: Odoo
Classifier: Framework :: Odoo :: 14.0
Classifier: License :: OSI Approved :: GNU Affero General Public License v3
Classifier: Development Status :: 5 - Production/Stable
Requires-Python: >=3.6
Requires-Dist: odoo14-addon-shopinvader-guest-mode
Requires-Dist: odoo14-addon-shopinvader-locomotive
Requires-Dist: odoo (<14.1dev,>=14.0a)
